distrolab/Binomialdistribution.py
distrolab/Gaussiandistribution.py
distrolab/Generaldistribution.py
distrolab/__init__.py
DistroLab-0.2.dist-info/METADATA
DistroLab-0.2.dist-info/WHEEL
DistroLab-0.2.dist-info/top_level.txt
DistroLab-0.2.dist-info/RECORD
