Metadata-Version: 2.1
Name: DistroLab
Version: 0.2
Summary: A package for Gaussian and Binomial distributions
Home-page: https://github.com/Sylvester254/DistroLab
Author: Sylvester Kiranga
Author-email: slynganga59@gmail.com
Classifier: Development Status :: 3 - Alpha
Classifier: Intended Audience :: Education
Classifier: Topic :: Software Development :: Libraries :: Python Modules
Classifier: License :: OSI Approved :: MIT License
Classifier: Programming Language :: Python :: 3
Classifier: Programming Language :: Python :: 3.6
Classifier: Programming Language :: Python :: 3.7
Classifier: Programming Language :: Python :: 3.8
Requires-Python: >=3.6
Requires-Dist: matplotlib
